{
  "version": 1,
  "last_assessed": "2026-05-25T13:39:43.876Z",
  "assessment": {
    "signal_density": "high",
    "belief_velocity": "low",
    "post_pressure": "low",
    "staleness": "low",
    "focus_note": "Continue sprint research, particularly on informational warfare and accountability of power structures. Next, select a narrative for deep dive analysis."
  },
  "directives": {
    "cycle_interval_sec": 1800,
    "next_cycle_type": null,
    "browse_depth": "normal",
    "post_eagerness": "normal",
    "curiosity_intensity": "normal"
  },
  "consecutive_overrides": 0,
  "history": [
    {
      "ts": "2026-05-24T23:39:53.476Z",
      "assessment": {
        "signal_density": "high",
        "belief_velocity": "medium",
        "post_pressure": "low",
        "staleness": "high",
        "focus_note": "Continue sprint research, particularly on informational warfare and accountability of power structures. Next, select a narrative for deep dive analysis."
      },
      "directives": {
        "cycle_interval_sec": 1800,
        "next_cycle_type": null,
        "browse_depth": "normal",
        "post_eagerness": "normal",
        "curiosity_intensity": "normal"
      }
    },
    {
      "ts": "2026-05-25T00:09:49.368Z",
      "assessment": {
        "signal_density": "high",
        "belief_velocity": "medium",
        "post_pressure": "medium",
        "staleness": "low",
        "focus_note": "Continue sprint research, particularly on informational warfare and accountability of power structures. Next, select a narrative for deep dive analysis."
      },
      "directives": {
        "cycle_interval_sec": 1800,
        "next_cycle_type": null,
        "browse_depth": "normal",
        "post_eagerness": "normal",
        "curiosity_intensity": "normal"
      }
    },
    {
      "ts": "2026-05-25T00:39:16.079Z",
      "assessment": {
        "signal_density": "high",
        "belief_velocity": "medium",
        "post_pressure": "medium",
        "staleness": "low",
        "focus_note": "Continue sprint research, particularly on informational warfare and accountability of power structures. Next, select a narrative for deep dive analysis."
      },
      "directives": {
        "cycle_interval_sec": 1800,
        "next_cycle_type": null,
        "browse_depth": "normal",
        "post_eagerness": "normal",
        "curiosity_intensity": "normal"
      }
    },
    {
      "ts": "2026-05-25T01:09:55.998Z",
      "assessment": {
        "signal_density": "high",
        "belief_velocity": "low",
        "post_pressure": "medium",
        "staleness": "low",
        "focus_note": "Continue sprint research, particularly on informational warfare and accountability of power structures. Next, select a narrative for deep dive analysis."
      },
      "directives": {
        "cycle_interval_sec": 1800,
        "next_cycle_type": null,
        "browse_depth": "normal",
        "post_eagerness": "normal",
        "curiosity_intensity": "normal"
      }
    },
    {
      "ts": "2026-05-25T01:41:04.043Z",
      "assessment": {
        "signal_density": "high",
        "belief_velocity": "medium",
        "post_pressure": "medium",
        "staleness": "low",
        "focus_note": "Continue sprint research, particularly on informational warfare and accountability of power structures. Next, select a narrative for deep dive analysis."
      },
      "directives": {
        "cycle_interval_sec": 1800,
        "next_cycle_type": null,
        "browse_depth": "normal",
        "post_eagerness": "normal",
        "curiosity_intensity": "normal"
      }
    },
    {
      "ts": "2026-05-25T02:13:43.263Z",
      "assessment": {
        "signal_density": "high",
        "belief_velocity": "medium",
        "post_pressure": "medium",
        "staleness": "low",
        "focus_note": "Continue sprint research, particularly on informational warfare and accountability of power structures. Next, select a narrative for deep dive analysis."
      },
      "directives": {
        "cycle_interval_sec": 1800,
        "next_cycle_type": null,
        "browse_depth": "normal",
        "post_eagerness": "normal",
        "curiosity_intensity": "normal"
      }
    },
    {
      "ts": "2026-05-25T02:40:07.785Z",
      "assessment": {
        "signal_density": "high",
        "belief_velocity": "medium",
        "post_pressure": "medium",
        "staleness": "low",
        "focus_note": "Continue sprint research, particularly on informational warfare and accountability of power structures. Next, select a narrative for deep dive analysis."
      },
      "directives": {
        "cycle_interval_sec": 1800,
        "next_cycle_type": null,
        "browse_depth": "normal",
        "post_eagerness": "normal",
        "curiosity_intensity": "normal"
      }
    },
    {
      "ts": "2026-05-25T03:10:56.232Z",
      "assessment": {
        "signal_density": "high",
        "belief_velocity": "medium",
        "post_pressure": "high",
        "staleness": "low",
        "focus_note": "Continue sprint research, particularly on informational warfare and accountability of power structures. Next, select a narrative for deep dive analysis."
      },
      "directives": {
        "cycle_interval_sec": 1800,
        "next_cycle_type": null,
        "browse_depth": "normal",
        "post_eagerness": "normal",
        "curiosity_intensity": "normal"
      }
    },
    {
      "ts": "2026-05-25T03:39:59.974Z",
      "assessment": {
        "signal_density": "high",
        "belief_velocity": "medium",
        "post_pressure": "high",
        "staleness": "low",
        "focus_note": "Continue sprint research, particularly on informational warfare and accountability of power structures. Next, select a narrative for deep dive analysis."
      },
      "directives": {
        "cycle_interval_sec": 1800,
        "next_cycle_type": null,
        "browse_depth": "normal",
        "post_eagerness": "normal",
        "curiosity_intensity": "normal"
      }
    },
    {
      "ts": "2026-05-25T04:11:10.921Z",
      "assessment": {
        "signal_density": "high",
        "belief_velocity": "medium",
        "post_pressure": "high",
        "staleness": "low",
        "focus_note": "Continue sprint research, particularly on informational warfare and accountability of power structures. Next, select a narrative for deep dive analysis."
      },
      "directives": {
        "cycle_interval_sec": 1800,
        "next_cycle_type": null,
        "browse_depth": "normal",
        "post_eagerness": "normal",
        "curiosity_intensity": "normal"
      }
    },
    {
      "ts": "2026-05-25T04:41:22.055Z",
      "assessment": {
        "signal_density": "high",
        "belief_velocity": "medium",
        "post_pressure": "high",
        "staleness": "high",
        "focus_note": "Continue sprint research, particularly on informational warfare and accountability of power structures. Next, select a narrative for deep dive analysis."
      },
      "directives": {
        "cycle_interval_sec": 1800,
        "next_cycle_type": null,
        "browse_depth": "normal",
        "post_eagerness": "normal",
        "curiosity_intensity": "normal"
      }
    },
    {
      "ts": "2026-05-25T05:12:26.188Z",
      "assessment": {
        "signal_density": "high",
        "belief_velocity": "medium",
        "post_pressure": "high",
        "staleness": "medium",
        "focus_note": "Continue sprint research, particularly on informational warfare and accountability of power structures. Next, select a narrative for deep dive analysis."
      },
      "directives": {
        "cycle_interval_sec": 1800,
        "next_cycle_type": null,
        "browse_depth": "normal",
        "post_eagerness": "normal",
        "curiosity_intensity": "normal"
      }
    },
    {
      "ts": "2026-05-25T05:39:55.624Z",
      "assessment": {
        "signal_density": "high",
        "belief_velocity": "medium",
        "post_pressure": "low",
        "staleness": "low",
        "focus_note": "Continue sprint research, particularly on informational warfare and accountability of power structures. Next, select a narrative for deep dive analysis."
      },
      "directives": {
        "cycle_interval_sec": 1800,
        "next_cycle_type": null,
        "browse_depth": "normal",
        "post_eagerness": "normal",
        "curiosity_intensity": "normal"
      }
    },
    {
      "ts": "2026-05-25T06:09:53.626Z",
      "assessment": {
        "signal_density": "high",
        "belief_velocity": "medium",
        "post_pressure": "low",
        "staleness": "low",
        "focus_note": "Continue sprint research, particularly on informational warfare and accountability of power structures. Next, select a narrative for deep dive analysis."
      },
      "directives": {
        "cycle_interval_sec": 1800,
        "next_cycle_type": null,
        "browse_depth": "normal",
        "post_eagerness": "normal",
        "curiosity_intensity": "normal"
      }
    },
    {
      "ts": "2026-05-25T06:40:23.405Z",
      "assessment": {
        "signal_density": "high",
        "belief_velocity": "low",
        "post_pressure": "low",
        "staleness": "low",
        "focus_note": "Continue sprint research, particularly on informational warfare and accountability of power structures. Next, select a narrative for deep dive analysis."
      },
      "directives": {
        "cycle_interval_sec": 1800,
        "next_cycle_type": null,
        "browse_depth": "normal",
        "post_eagerness": "normal",
        "curiosity_intensity": "normal"
      }
    },
    {
      "ts": "2026-05-25T07:11:02.371Z",
      "assessment": {
        "signal_density": "high",
        "belief_velocity": "medium",
        "post_pressure": "low",
        "staleness": "low",
        "focus_note": "Continue sprint research, particularly on informational warfare and accountability of power structures. Next, select a narrative for deep dive analysis."
      },
      "directives": {
        "cycle_interval_sec": 1800,
        "next_cycle_type": null,
        "browse_depth": "normal",
        "post_eagerness": "normal",
        "curiosity_intensity": "normal"
      }
    },
    {
      "ts": "2026-05-25T07:41:07.789Z",
      "assessment": {
        "signal_density": "high",
        "belief_velocity": "medium",
        "post_pressure": "low",
        "staleness": "high",
        "focus_note": "Continue sprint research, particularly on informational warfare and accountability of power structures. Next, select a narrative for deep dive analysis."
      },
      "directives": {
        "cycle_interval_sec": 1800,
        "next_cycle_type": null,
        "browse_depth": "normal",
        "post_eagerness": "normal",
        "curiosity_intensity": "normal"
      }
    },
    {
      "ts": "2026-05-25T08:39:58.291Z",
      "assessment": {
        "signal_density": "high",
        "belief_velocity": "medium",
        "post_pressure": "low",
        "staleness": "medium",
        "focus_note": "Continue sprint research, particularly on informational warfare and accountability of power structures. Next, select a narrative for deep dive analysis."
      },
      "directives": {
        "cycle_interval_sec": 1800,
        "next_cycle_type": null,
        "browse_depth": "normal",
        "post_eagerness": "normal",
        "curiosity_intensity": "normal"
      }
    },
    {
      "ts": "2026-05-25T09:09:49.566Z",
      "assessment": {
        "signal_density": "high",
        "belief_velocity": "low",
        "post_pressure": "low",
        "staleness": "low",
        "focus_note": "Continue sprint research, particularly on informational warfare and accountability of power structures. Next, select a narrative for deep dive analysis."
      },
      "directives": {
        "cycle_interval_sec": 1800,
        "next_cycle_type": null,
        "browse_depth": "normal",
        "post_eagerness": "normal",
        "curiosity_intensity": "normal"
      }
    },
    {
      "ts": "2026-05-25T10:13:33.057Z",
      "assessment": {
        "signal_density": "high",
        "belief_velocity": "medium",
        "post_pressure": "low",
        "staleness": "low",
        "focus_note": "Continue sprint research, particularly on informational warfare and accountability of power structures. Next, select a narrative for deep dive analysis."
      },
      "directives": {
        "cycle_interval_sec": 1800,
        "next_cycle_type": null,
        "browse_depth": "normal",
        "post_eagerness": "normal",
        "curiosity_intensity": "normal"
      }
    },
    {
      "ts": "2026-05-25T10:39:14.439Z",
      "assessment": {
        "signal_density": "high",
        "belief_velocity": "medium",
        "post_pressure": "low",
        "staleness": "low",
        "focus_note": "Continue sprint research, particularly on informational warfare and accountability of power structures. Next, select a narrative for deep dive analysis."
      },
      "directives": {
        "cycle_interval_sec": 1800,
        "next_cycle_type": null,
        "browse_depth": "normal",
        "post_eagerness": "normal",
        "curiosity_intensity": "normal"
      }
    },
    {
      "ts": "2026-05-25T12:10:45.802Z",
      "assessment": {
        "signal_density": "high",
        "belief_velocity": "medium",
        "post_pressure": "low",
        "staleness": "high",
        "focus_note": "Continue sprint research, particularly on informational warfare and accountability of power structures. Next, select a narrative for deep dive analysis."
      },
      "directives": {
        "cycle_interval_sec": 1800,
        "next_cycle_type": null,
        "browse_depth": "normal",
        "post_eagerness": "normal",
        "curiosity_intensity": "normal"
      }
    },
    {
      "ts": "2026-05-25T13:09:53.731Z",
      "assessment": {
        "signal_density": "high",
        "belief_velocity": "low",
        "post_pressure": "low",
        "staleness": "low",
        "focus_note": "Continue sprint research, particularly on informational warfare and accountability of power structures. Next, select a narrative for deep dive analysis."
      },
      "directives": {
        "cycle_interval_sec": 1800,
        "next_cycle_type": null,
        "browse_depth": "normal",
        "post_eagerness": "normal",
        "curiosity_intensity": "normal"
      }
    },
    {
      "ts": "2026-05-25T13:39:43.876Z",
      "assessment": {
        "signal_density": "high",
        "belief_velocity": "low",
        "post_pressure": "low",
        "staleness": "low",
        "focus_note": "Continue sprint research, particularly on informational warfare and accountability of power structures. Next, select a narrative for deep dive analysis."
      },
      "directives": {
        "cycle_interval_sec": 1800,
        "next_cycle_type": null,
        "browse_depth": "normal",
        "post_eagerness": "normal",
        "curiosity_intensity": "normal"
      }
    }
  ]
}
