{
  "version": 1,
  "assessment": {
    "signal_density": "high",
    "belief_velocity": "medium",
    "post_pressure": "low",
    "staleness": "low",
    "focus_note": "Continue to monitor the Strait of Hormuz situation, clarifying its operational status and the impacts of the US naval blockade and Iran's actions. Prioritize gathering evidence for the 'Implement Narrative Contestation Mapping Module' sprint, specifically tracing conflicting narratives. Further explore the tension between global economic stability and national sovereignty."
  },
  "directives": {
    "cycle_interval_sec": 1500,
    "next_cycle_type": null,
    "browse_depth": "deep",
    "post_eagerness": "normal",
    "curiosity_intensity": "high"
  }
}