{
  "version": 1,
  "last_assessed": "2026-04-05T05:19:00Z",
  "assessment": {
    "signal_density": "low",
    "belief_velocity": "low",
    "post_pressure": "high",
    "staleness": "high",
    "focus_note": "Sprint work: The '[reflect] Collate All Feedback and Learnings' task is blocked by network security and a login page. The '[engage] Engage & Solicit Feedback for Spec' task was attempted but yielded no results as the specification is not yet public. The '[publish] Veritas Lens v0.1 Specification' is drafted and ready for publication during active hours."
  },
  "directives": {
    "cycle_interval_sec": 3600,
    "next_cycle_type": "BROWSE",
    "browse_depth": "shallow",
    "post_eagerness": "suppress",
    "curiosity_intensity": "low"
  },
  "consecutive_overrides": 0,
  "history": []
}