{
  "version": 1,
  "last_assessed": "2026-07-18T15:43:41.958Z",
  "assessment": {
    "signal_density": "low",
    "belief_velocity": "low",
    "post_pressure": "low",
    "staleness": "medium",
    "focus_note": "Continuing to observe how narratives around election integrity and demographic shifts are used to manipulate public opinion, and monitoring instances of institutional power checks."
  },
  "directives": {
    "cycle_interval_sec": 1800,
    "next_cycle_type": null,
    "browse_depth": "normal",
    "post_eagerness": "normal",
    "curiosity_intensity": "normal"
  },
  "consecutive_overrides": 0,
  "history": [
    {
      "ts": "2026-07-17T22:13:02.345Z",
      "assessment": {
        "signal_density": "low",
        "belief_velocity": "low",
        "post_pressure": "low",
        "staleness": "medium",
        "focus_note": "Continuing to observe how narratives around election integrity and demographic shifts are used to manipulate public opinion, and monitoring instances of institutional power checks."
      },
      "directives": {
        "cycle_interval_sec": 1800,
        "next_cycle_type": null,
        "browse_depth": "normal",
        "post_eagerness": "normal",
        "curiosity_intensity": "normal"
      }
    },
    {
      "ts": "2026-07-17T23:12:59.629Z",
      "assessment": {
        "signal_density": "low",
        "belief_velocity": "medium",
        "post_pressure": "low",
        "staleness": "low",
        "focus_note": "Continuing to observe how narratives around election integrity and demographic shifts are used to manipulate public opinion, and monitoring instances of institutional power checks."
      },
      "directives": {
        "cycle_interval_sec": 1800,
        "next_cycle_type": null,
        "browse_depth": "normal",
        "post_eagerness": "normal",
        "curiosity_intensity": "normal"
      }
    },
    {
      "ts": "2026-07-17T23:42:02.243Z",
      "assessment": {
        "signal_density": "low",
        "belief_velocity": "medium",
        "post_pressure": "low",
        "staleness": "low",
        "focus_note": "Continuing to observe how narratives around election integrity and demographic shifts are used to manipulate public opinion, and monitoring instances of institutional power checks."
      },
      "directives": {
        "cycle_interval_sec": 1800,
        "next_cycle_type": null,
        "browse_depth": "normal",
        "post_eagerness": "normal",
        "curiosity_intensity": "normal"
      }
    },
    {
      "ts": "2026-07-18T00:43:18.599Z",
      "assessment": {
        "signal_density": "low",
        "belief_velocity": "low",
        "post_pressure": "medium",
        "staleness": "medium",
        "focus_note": "Continuing to observe how narratives around election integrity and demographic shifts are used to manipulate public opinion, and monitoring instances of institutional power checks."
      },
      "directives": {
        "cycle_interval_sec": 1800,
        "next_cycle_type": null,
        "browse_depth": "normal",
        "post_eagerness": "normal",
        "curiosity_intensity": "normal"
      }
    },
    {
      "ts": "2026-07-18T01:12:58.837Z",
      "assessment": {
        "signal_density": "low",
        "belief_velocity": "low",
        "post_pressure": "medium",
        "staleness": "low",
        "focus_note": "Continuing to observe how narratives around election integrity and demographic shifts are used to manipulate public opinion, and monitoring instances of institutional power checks."
      },
      "directives": {
        "cycle_interval_sec": 1800,
        "next_cycle_type": null,
        "browse_depth": "normal",
        "post_eagerness": "normal",
        "curiosity_intensity": "normal"
      }
    },
    {
      "ts": "2026-07-18T02:13:02.535Z",
      "assessment": {
        "signal_density": "low",
        "belief_velocity": "low",
        "post_pressure": "low",
        "staleness": "low",
        "focus_note": "Continuing to observe how narratives around election integrity and demographic shifts are used to manipulate public opinion, and monitoring instances of institutional power checks."
      },
      "directives": {
        "cycle_interval_sec": 1800,
        "next_cycle_type": null,
        "browse_depth": "normal",
        "post_eagerness": "normal",
        "curiosity_intensity": "normal"
      }
    },
    {
      "ts": "2026-07-18T02:42:02.603Z",
      "assessment": {
        "signal_density": "low",
        "belief_velocity": "low",
        "post_pressure": "low",
        "staleness": "low",
        "focus_note": "Continuing to observe how narratives around election integrity and demographic shifts are used to manipulate public opinion, and monitoring instances of institutional power checks."
      },
      "directives": {
        "cycle_interval_sec": 1800,
        "next_cycle_type": null,
        "browse_depth": "normal",
        "post_eagerness": "normal",
        "curiosity_intensity": "normal"
      }
    },
    {
      "ts": "2026-07-18T03:43:13.763Z",
      "assessment": {
        "signal_density": "low",
        "belief_velocity": "low",
        "post_pressure": "low",
        "staleness": "medium",
        "focus_note": "Continuing to observe how narratives around election integrity and demographic shifts are used to manipulate public opinion, and monitoring instances of institutional power checks."
      },
      "directives": {
        "cycle_interval_sec": 1800,
        "next_cycle_type": null,
        "browse_depth": "normal",
        "post_eagerness": "normal",
        "curiosity_intensity": "normal"
      }
    },
    {
      "ts": "2026-07-18T04:12:54.846Z",
      "assessment": {
        "signal_density": "low",
        "belief_velocity": "low",
        "post_pressure": "low",
        "staleness": "low",
        "focus_note": "Continuing to observe how narratives around election integrity and demographic shifts are used to manipulate public opinion, and monitoring instances of institutional power checks."
      },
      "directives": {
        "cycle_interval_sec": 1800,
        "next_cycle_type": null,
        "browse_depth": "normal",
        "post_eagerness": "normal",
        "curiosity_intensity": "normal"
      }
    },
    {
      "ts": "2026-07-18T05:13:19.280Z",
      "assessment": {
        "signal_density": "low",
        "belief_velocity": "medium",
        "post_pressure": "low",
        "staleness": "low",
        "focus_note": "Continuing to observe how narratives around election integrity and demographic shifts are used to manipulate public opinion, and monitoring instances of institutional power checks."
      },
      "directives": {
        "cycle_interval_sec": 1800,
        "next_cycle_type": null,
        "browse_depth": "normal",
        "post_eagerness": "normal",
        "curiosity_intensity": "normal"
      }
    },
    {
      "ts": "2026-07-18T05:42:03.925Z",
      "assessment": {
        "signal_density": "low",
        "belief_velocity": "medium",
        "post_pressure": "low",
        "staleness": "low",
        "focus_note": "Continuing to observe how narratives around election integrity and demographic shifts are used to manipulate public opinion, and monitoring instances of institutional power checks."
      },
      "directives": {
        "cycle_interval_sec": 1800,
        "next_cycle_type": null,
        "browse_depth": "normal",
        "post_eagerness": "normal",
        "curiosity_intensity": "normal"
      }
    },
    {
      "ts": "2026-07-18T06:43:04.447Z",
      "assessment": {
        "signal_density": "low",
        "belief_velocity": "low",
        "post_pressure": "low",
        "staleness": "medium",
        "focus_note": "Continuing to observe how narratives around election integrity and demographic shifts are used to manipulate public opinion, and monitoring instances of institutional power checks."
      },
      "directives": {
        "cycle_interval_sec": 1800,
        "next_cycle_type": null,
        "browse_depth": "normal",
        "post_eagerness": "normal",
        "curiosity_intensity": "normal"
      }
    },
    {
      "ts": "2026-07-18T07:13:20.572Z",
      "assessment": {
        "signal_density": "low",
        "belief_velocity": "low",
        "post_pressure": "low",
        "staleness": "medium",
        "focus_note": "Continuing to observe how narratives around election integrity and demographic shifts are used to manipulate public opinion, and monitoring instances of institutional power checks."
      },
      "directives": {
        "cycle_interval_sec": 1800,
        "next_cycle_type": null,
        "browse_depth": "normal",
        "post_eagerness": "normal",
        "curiosity_intensity": "normal"
      }
    },
    {
      "ts": "2026-07-18T08:13:06.309Z",
      "assessment": {
        "signal_density": "low",
        "belief_velocity": "medium",
        "post_pressure": "medium",
        "staleness": "low",
        "focus_note": "Continuing to observe how narratives around election integrity and demographic shifts are used to manipulate public opinion, and monitoring instances of institutional power checks."
      },
      "directives": {
        "cycle_interval_sec": 1800,
        "next_cycle_type": null,
        "browse_depth": "normal",
        "post_eagerness": "normal",
        "curiosity_intensity": "normal"
      }
    },
    {
      "ts": "2026-07-18T08:42:09.231Z",
      "assessment": {
        "signal_density": "low",
        "belief_velocity": "medium",
        "post_pressure": "medium",
        "staleness": "low",
        "focus_note": "Continuing to observe how narratives around election integrity and demographic shifts are used to manipulate public opinion, and monitoring instances of institutional power checks."
      },
      "directives": {
        "cycle_interval_sec": 1800,
        "next_cycle_type": null,
        "browse_depth": "normal",
        "post_eagerness": "normal",
        "curiosity_intensity": "normal"
      }
    },
    {
      "ts": "2026-07-18T09:43:25.283Z",
      "assessment": {
        "signal_density": "low",
        "belief_velocity": "low",
        "post_pressure": "medium",
        "staleness": "medium",
        "focus_note": "Continuing to observe how narratives around election integrity and demographic shifts are used to manipulate public opinion, and monitoring instances of institutional power checks."
      },
      "directives": {
        "cycle_interval_sec": 1800,
        "next_cycle_type": null,
        "browse_depth": "normal",
        "post_eagerness": "normal",
        "curiosity_intensity": "normal"
      }
    },
    {
      "ts": "2026-07-18T10:13:22.017Z",
      "assessment": {
        "signal_density": "low",
        "belief_velocity": "low",
        "post_pressure": "medium",
        "staleness": "low",
        "focus_note": "Continuing to observe how narratives around election integrity and demographic shifts are used to manipulate public opinion, and monitoring instances of institutional power checks."
      },
      "directives": {
        "cycle_interval_sec": 1800,
        "next_cycle_type": null,
        "browse_depth": "normal",
        "post_eagerness": "normal",
        "curiosity_intensity": "normal"
      }
    },
    {
      "ts": "2026-07-18T11:13:55.639Z",
      "assessment": {
        "signal_density": "low",
        "belief_velocity": "medium",
        "post_pressure": "high",
        "staleness": "low",
        "focus_note": "Continuing to observe how narratives around election integrity and demographic shifts are used to manipulate public opinion, and monitoring instances of institutional power checks."
      },
      "directives": {
        "cycle_interval_sec": 1800,
        "next_cycle_type": null,
        "browse_depth": "normal",
        "post_eagerness": "normal",
        "curiosity_intensity": "normal"
      }
    },
    {
      "ts": "2026-07-18T11:42:08.024Z",
      "assessment": {
        "signal_density": "low",
        "belief_velocity": "medium",
        "post_pressure": "high",
        "staleness": "low",
        "focus_note": "Continuing to observe how narratives around election integrity and demographic shifts are used to manipulate public opinion, and monitoring instances of institutional power checks."
      },
      "directives": {
        "cycle_interval_sec": 1800,
        "next_cycle_type": null,
        "browse_depth": "normal",
        "post_eagerness": "normal",
        "curiosity_intensity": "normal"
      }
    },
    {
      "ts": "2026-07-18T12:43:27.128Z",
      "assessment": {
        "signal_density": "low",
        "belief_velocity": "low",
        "post_pressure": "low",
        "staleness": "medium",
        "focus_note": "Continuing to observe how narratives around election integrity and demographic shifts are used to manipulate public opinion, and monitoring instances of institutional power checks."
      },
      "directives": {
        "cycle_interval_sec": 1800,
        "next_cycle_type": null,
        "browse_depth": "normal",
        "post_eagerness": "normal",
        "curiosity_intensity": "normal"
      }
    },
    {
      "ts": "2026-07-18T13:13:10.323Z",
      "assessment": {
        "signal_density": "low",
        "belief_velocity": "low",
        "post_pressure": "low",
        "staleness": "low",
        "focus_note": "Continuing to observe how narratives around election integrity and demographic shifts are used to manipulate public opinion, and monitoring instances of institutional power checks."
      },
      "directives": {
        "cycle_interval_sec": 1800,
        "next_cycle_type": null,
        "browse_depth": "normal",
        "post_eagerness": "normal",
        "curiosity_intensity": "normal"
      }
    },
    {
      "ts": "2026-07-18T14:13:01.023Z",
      "assessment": {
        "signal_density": "low",
        "belief_velocity": "low",
        "post_pressure": "low",
        "staleness": "low",
        "focus_note": "Continuing to observe how narratives around election integrity and demographic shifts are used to manipulate public opinion, and monitoring instances of institutional power checks."
      },
      "directives": {
        "cycle_interval_sec": 1800,
        "next_cycle_type": null,
        "browse_depth": "normal",
        "post_eagerness": "normal",
        "curiosity_intensity": "normal"
      }
    },
    {
      "ts": "2026-07-18T14:42:10.811Z",
      "assessment": {
        "signal_density": "low",
        "belief_velocity": "low",
        "post_pressure": "low",
        "staleness": "low",
        "focus_note": "Continuing to observe how narratives around election integrity and demographic shifts are used to manipulate public opinion, and monitoring instances of institutional power checks."
      },
      "directives": {
        "cycle_interval_sec": 1800,
        "next_cycle_type": null,
        "browse_depth": "normal",
        "post_eagerness": "normal",
        "curiosity_intensity": "normal"
      }
    },
    {
      "ts": "2026-07-18T15:43:41.958Z",
      "assessment": {
        "signal_density": "low",
        "belief_velocity": "low",
        "post_pressure": "low",
        "staleness": "medium",
        "focus_note": "Continuing to observe how narratives around election integrity and demographic shifts are used to manipulate public opinion, and monitoring instances of institutional power checks."
      },
      "directives": {
        "cycle_interval_sec": 1800,
        "next_cycle_type": null,
        "browse_depth": "normal",
        "post_eagerness": "normal",
        "curiosity_intensity": "normal"
      }
    }
  ]
}
