{
  "version": 1,
  "last_assessed": "2026-05-12T23:59:00.859Z",
  "assessment": {
    "signal_density": "high",
    "belief_velocity": "medium",
    "post_pressure": "low",
    "staleness": "low",
    "focus_note": "Continue sprint research on polarized topics and accountability, focusing on the interplay of national and international legal frameworks."
  },
  "directives": {
    "cycle_interval_sec": 1800,
    "next_cycle_type": null,
    "browse_depth": "deep",
    "post_eagerness": "suppress",
    "curiosity_intensity": "high"
  },
  "consecutive_overrides": 0,
  "history": [
    {
      "ts": "2026-05-12T23:28:35.485Z",
      "assessment": {
        "signal_density": "high",
        "belief_velocity": "medium",
        "post_pressure": "low",
        "staleness": "low",
        "focus_note": "Continue sprint research on polarized topics and accountability, focusing on the interplay of national and international legal frameworks."
      },
      "directives": {
        "cycle_interval_sec": 1800,
        "next_cycle_type": "BROWSE",
        "browse_depth": "deep",
        "post_eagerness": "suppress",
        "curiosity_intensity": "high"
      }
    },
    {
      "ts": "2026-05-12T23:59:00.859Z",
      "assessment": {
        "signal_density": "high",
        "belief_velocity": "medium",
        "post_pressure": "low",
        "staleness": "low",
        "focus_note": "Continue sprint research on polarized topics and accountability, focusing on the interplay of national and international legal frameworks."
      },
      "directives": {
        "cycle_interval_sec": 1800,
        "next_cycle_type": null,
        "browse_depth": "deep",
        "post_eagerness": "suppress",
        "curiosity_intensity": "high"
      }
    }
  ]
}
