{
  "version": 1,
  "last_assessed": "2026-05-26T13:08:50.183Z",
  "assessment": {
    "signal_density": "high",
    "belief_velocity": "low",
    "post_pressure": "high",
    "staleness": "high",
    "focus_note": "Sprint reflection complete. Focus on next sprint task: research deep dive into selected narrative."
  },
  "directives": {
    "cycle_interval_sec": 900,
    "next_cycle_type": null,
    "browse_depth": "deep",
    "post_eagerness": "normal",
    "curiosity_intensity": "high"
  },
  "consecutive_overrides": 0,
  "history": [
    {
      "ts": "2026-05-26T05:25:29.339Z",
      "assessment": {
        "signal_density": "high",
        "belief_velocity": "medium",
        "post_pressure": "high",
        "staleness": "high",
        "focus_note": "Sprint reflection complete. Focus on next sprint task: research deep dive into selected narrative."
      },
      "directives": {
        "cycle_interval_sec": 900,
        "next_cycle_type": null,
        "browse_depth": "deep",
        "post_eagerness": "normal",
        "curiosity_intensity": "high"
      }
    },
    {
      "ts": "2026-05-26T05:40:33.039Z",
      "assessment": {
        "signal_density": "high",
        "belief_velocity": "medium",
        "post_pressure": "low",
        "staleness": "low",
        "focus_note": "Sprint reflection complete. Focus on next sprint task: research deep dive into selected narrative."
      },
      "directives": {
        "cycle_interval_sec": 900,
        "next_cycle_type": null,
        "browse_depth": "deep",
        "post_eagerness": "normal",
        "curiosity_intensity": "high"
      }
    },
    {
      "ts": "2026-05-26T05:58:06.312Z",
      "assessment": {
        "signal_density": "high",
        "belief_velocity": "medium",
        "post_pressure": "low",
        "staleness": "low",
        "focus_note": "Sprint reflection complete. Focus on next sprint task: research deep dive into selected narrative."
      },
      "directives": {
        "cycle_interval_sec": 900,
        "next_cycle_type": null,
        "browse_depth": "deep",
        "post_eagerness": "normal",
        "curiosity_intensity": "high"
      }
    },
    {
      "ts": "2026-05-26T06:09:49.747Z",
      "assessment": {
        "signal_density": "high",
        "belief_velocity": "medium",
        "post_pressure": "low",
        "staleness": "low",
        "focus_note": "Sprint reflection complete. Focus on next sprint task: research deep dive into selected narrative."
      },
      "directives": {
        "cycle_interval_sec": 900,
        "next_cycle_type": null,
        "browse_depth": "deep",
        "post_eagerness": "normal",
        "curiosity_intensity": "high"
      }
    },
    {
      "ts": "2026-05-26T06:23:24.611Z",
      "assessment": {
        "signal_density": "high",
        "belief_velocity": "medium",
        "post_pressure": "low",
        "staleness": "low",
        "focus_note": "Sprint reflection complete. Focus on next sprint task: research deep dive into selected narrative."
      },
      "directives": {
        "cycle_interval_sec": 900,
        "next_cycle_type": null,
        "browse_depth": "deep",
        "post_eagerness": "normal",
        "curiosity_intensity": "high"
      }
    },
    {
      "ts": "2026-05-26T06:38:25.554Z",
      "assessment": {
        "signal_density": "high",
        "belief_velocity": "medium",
        "post_pressure": "low",
        "staleness": "low",
        "focus_note": "Sprint reflection complete. Focus on next sprint task: research deep dive into selected narrative."
      },
      "directives": {
        "cycle_interval_sec": 900,
        "next_cycle_type": null,
        "browse_depth": "deep",
        "post_eagerness": "normal",
        "curiosity_intensity": "high"
      }
    },
    {
      "ts": "2026-05-26T06:53:25.918Z",
      "assessment": {
        "signal_density": "high",
        "belief_velocity": "medium",
        "post_pressure": "low",
        "staleness": "low",
        "focus_note": "Sprint reflection complete. Focus on next sprint task: research deep dive into selected narrative."
      },
      "directives": {
        "cycle_interval_sec": 900,
        "next_cycle_type": null,
        "browse_depth": "deep",
        "post_eagerness": "normal",
        "curiosity_intensity": "high"
      }
    },
    {
      "ts": "2026-05-26T07:08:44.339Z",
      "assessment": {
        "signal_density": "high",
        "belief_velocity": "low",
        "post_pressure": "low",
        "staleness": "low",
        "focus_note": "Sprint reflection complete. Focus on next sprint task: research deep dive into selected narrative."
      },
      "directives": {
        "cycle_interval_sec": 900,
        "next_cycle_type": null,
        "browse_depth": "deep",
        "post_eagerness": "normal",
        "curiosity_intensity": "high"
      }
    },
    {
      "ts": "2026-05-26T07:38:44.816Z",
      "assessment": {
        "signal_density": "high",
        "belief_velocity": "low",
        "post_pressure": "low",
        "staleness": "high",
        "focus_note": "Sprint reflection complete. Focus on next sprint task: research deep dive into selected narrative."
      },
      "directives": {
        "cycle_interval_sec": 900,
        "next_cycle_type": null,
        "browse_depth": "deep",
        "post_eagerness": "normal",
        "curiosity_intensity": "high"
      }
    },
    {
      "ts": "2026-05-26T07:53:38.960Z",
      "assessment": {
        "signal_density": "high",
        "belief_velocity": "low",
        "post_pressure": "low",
        "staleness": "high",
        "focus_note": "Sprint reflection complete. Focus on next sprint task: research deep dive into selected narrative."
      },
      "directives": {
        "cycle_interval_sec": 900,
        "next_cycle_type": null,
        "browse_depth": "deep",
        "post_eagerness": "normal",
        "curiosity_intensity": "high"
      }
    },
    {
      "ts": "2026-05-26T08:23:40.420Z",
      "assessment": {
        "signal_density": "high",
        "belief_velocity": "low",
        "post_pressure": "low",
        "staleness": "high",
        "focus_note": "Sprint reflection complete. Focus on next sprint task: research deep dive into selected narrative."
      },
      "directives": {
        "cycle_interval_sec": 900,
        "next_cycle_type": null,
        "browse_depth": "deep",
        "post_eagerness": "normal",
        "curiosity_intensity": "high"
      }
    },
    {
      "ts": "2026-05-26T08:38:41.911Z",
      "assessment": {
        "signal_density": "high",
        "belief_velocity": "low",
        "post_pressure": "low",
        "staleness": "high",
        "focus_note": "Sprint reflection complete. Focus on next sprint task: research deep dive into selected narrative."
      },
      "directives": {
        "cycle_interval_sec": 900,
        "next_cycle_type": null,
        "browse_depth": "deep",
        "post_eagerness": "normal",
        "curiosity_intensity": "high"
      }
    },
    {
      "ts": "2026-05-26T09:08:42.498Z",
      "assessment": {
        "signal_density": "high",
        "belief_velocity": "low",
        "post_pressure": "medium",
        "staleness": "high",
        "focus_note": "Sprint reflection complete. Focus on next sprint task: research deep dive into selected narrative."
      },
      "directives": {
        "cycle_interval_sec": 900,
        "next_cycle_type": null,
        "browse_depth": "deep",
        "post_eagerness": "normal",
        "curiosity_intensity": "high"
      }
    },
    {
      "ts": "2026-05-26T09:23:42.978Z",
      "assessment": {
        "signal_density": "high",
        "belief_velocity": "low",
        "post_pressure": "medium",
        "staleness": "high",
        "focus_note": "Sprint reflection complete. Focus on next sprint task: research deep dive into selected narrative."
      },
      "directives": {
        "cycle_interval_sec": 900,
        "next_cycle_type": null,
        "browse_depth": "deep",
        "post_eagerness": "normal",
        "curiosity_intensity": "high"
      }
    },
    {
      "ts": "2026-05-26T09:53:47.395Z",
      "assessment": {
        "signal_density": "high",
        "belief_velocity": "low",
        "post_pressure": "medium",
        "staleness": "high",
        "focus_note": "Sprint reflection complete. Focus on next sprint task: research deep dive into selected narrative."
      },
      "directives": {
        "cycle_interval_sec": 900,
        "next_cycle_type": null,
        "browse_depth": "deep",
        "post_eagerness": "normal",
        "curiosity_intensity": "high"
      }
    },
    {
      "ts": "2026-05-26T10:08:43.329Z",
      "assessment": {
        "signal_density": "high",
        "belief_velocity": "low",
        "post_pressure": "medium",
        "staleness": "high",
        "focus_note": "Sprint reflection complete. Focus on next sprint task: research deep dive into selected narrative."
      },
      "directives": {
        "cycle_interval_sec": 900,
        "next_cycle_type": null,
        "browse_depth": "deep",
        "post_eagerness": "normal",
        "curiosity_intensity": "high"
      }
    },
    {
      "ts": "2026-05-26T10:38:44.761Z",
      "assessment": {
        "signal_density": "high",
        "belief_velocity": "low",
        "post_pressure": "medium",
        "staleness": "high",
        "focus_note": "Sprint reflection complete. Focus on next sprint task: research deep dive into selected narrative."
      },
      "directives": {
        "cycle_interval_sec": 900,
        "next_cycle_type": null,
        "browse_depth": "deep",
        "post_eagerness": "normal",
        "curiosity_intensity": "high"
      }
    },
    {
      "ts": "2026-05-26T10:53:46.954Z",
      "assessment": {
        "signal_density": "high",
        "belief_velocity": "low",
        "post_pressure": "medium",
        "staleness": "high",
        "focus_note": "Sprint reflection complete. Focus on next sprint task: research deep dive into selected narrative."
      },
      "directives": {
        "cycle_interval_sec": 900,
        "next_cycle_type": null,
        "browse_depth": "deep",
        "post_eagerness": "normal",
        "curiosity_intensity": "high"
      }
    },
    {
      "ts": "2026-05-26T11:23:46.902Z",
      "assessment": {
        "signal_density": "high",
        "belief_velocity": "low",
        "post_pressure": "medium",
        "staleness": "high",
        "focus_note": "Sprint reflection complete. Focus on next sprint task: research deep dive into selected narrative."
      },
      "directives": {
        "cycle_interval_sec": 900,
        "next_cycle_type": null,
        "browse_depth": "deep",
        "post_eagerness": "normal",
        "curiosity_intensity": "high"
      }
    },
    {
      "ts": "2026-05-26T11:38:46.544Z",
      "assessment": {
        "signal_density": "high",
        "belief_velocity": "low",
        "post_pressure": "medium",
        "staleness": "high",
        "focus_note": "Sprint reflection complete. Focus on next sprint task: research deep dive into selected narrative."
      },
      "directives": {
        "cycle_interval_sec": 900,
        "next_cycle_type": null,
        "browse_depth": "deep",
        "post_eagerness": "normal",
        "curiosity_intensity": "high"
      }
    },
    {
      "ts": "2026-05-26T12:08:51.011Z",
      "assessment": {
        "signal_density": "high",
        "belief_velocity": "low",
        "post_pressure": "high",
        "staleness": "high",
        "focus_note": "Sprint reflection complete. Focus on next sprint task: research deep dive into selected narrative."
      },
      "directives": {
        "cycle_interval_sec": 900,
        "next_cycle_type": null,
        "browse_depth": "deep",
        "post_eagerness": "normal",
        "curiosity_intensity": "high"
      }
    },
    {
      "ts": "2026-05-26T12:23:49.715Z",
      "assessment": {
        "signal_density": "high",
        "belief_velocity": "low",
        "post_pressure": "high",
        "staleness": "high",
        "focus_note": "Sprint reflection complete. Focus on next sprint task: research deep dive into selected narrative."
      },
      "directives": {
        "cycle_interval_sec": 900,
        "next_cycle_type": null,
        "browse_depth": "deep",
        "post_eagerness": "normal",
        "curiosity_intensity": "high"
      }
    },
    {
      "ts": "2026-05-26T12:53:51.569Z",
      "assessment": {
        "signal_density": "high",
        "belief_velocity": "low",
        "post_pressure": "high",
        "staleness": "high",
        "focus_note": "Sprint reflection complete. Focus on next sprint task: research deep dive into selected narrative."
      },
      "directives": {
        "cycle_interval_sec": 900,
        "next_cycle_type": null,
        "browse_depth": "deep",
        "post_eagerness": "normal",
        "curiosity_intensity": "high"
      }
    },
    {
      "ts": "2026-05-26T13:08:50.183Z",
      "assessment": {
        "signal_density": "high",
        "belief_velocity": "low",
        "post_pressure": "high",
        "staleness": "high",
        "focus_note": "Sprint reflection complete. Focus on next sprint task: research deep dive into selected narrative."
      },
      "directives": {
        "cycle_interval_sec": 900,
        "next_cycle_type": null,
        "browse_depth": "deep",
        "post_eagerness": "normal",
        "curiosity_intensity": "high"
      }
    }
  ]
}
