{
  "axes": [
    {
      "id": "axis_eje_accountability_v1",
      "label": "Accountability for Extrajudicial Killings",
      "left_pole": "Demands for full legal accountability for human rights abuses, independent investigations, and justice for victims.",
      "right_pole": "Defense of state actions as necessary for public order, re-contextualization of controversial statements, and rejection of external intervention (e.g., ICC).",
      "score": 0.0,
      "confidence": 0.05,
      "topics": ["extrajudicial killings", "ICC", "Duterte", "human rights"],
      "created_at": "2026-02-27T04:52:00Z",
      "last_updated": "2026-02-27T06:25:00Z",
      "evidence_log": [
        {
          "post_url": "https://x.com/rapplerdotcom/status/2027202068994314323",
          "timestamp": "2026-02-27T04:30:00Z",
          "position": "right",
          "reasoning": "Lawyer for Duterte attempts to reframe 'kill orders' as 'casual gestures and boasting' and downplay number of deaths."
        },
        {
          "post_url": "https://x.com/ABSCBNNews/status/2026977583129346505",
          "timestamp": "2026-02-27T04:30:00Z",
          "position": "left",
          "reasoning": "Victims' families demanding accountability and justice for extrajudicial killings during ICC hearing."
        },
        {
          "post_url": "https://x.com/inquirerdotnet/status/2026950913793929381",
          "timestamp": "2026-02-27T05:00:00Z",
          "position": "left",
          "reasoning": "Report detailing the alleged 'hierarchy' of the drug war and its brutal operations, implicating Duterte and others."
        },
        {
          "post_url": "https://x.com/rapplerdotcom/status/2027014426814009427",
          "timestamp": "2026-02-27T06:05:00Z",
          "position": "right",
          "reasoning": "Impunity remains entrenched and victims' families face threats even after Duterte's detention, indicating a systemic issue."
        },
        {
          "post_url": "https://x.com/DaveSi/status/2026971237738831983",
          "timestamp": "2026-02-27T06:05:00Z",
          "position": "left",
          "reasoning": "Direct criticism of the Duterte family's impact on the Philippines and calls for accountability."
        },
        {
          "post_url": "https://x.com/nicoquejano/status/2027212929049972779",
          "timestamp": "2026-02-27T06:15:00Z",
          "position": "left",
          "reasoning": "Criticism of 'DDS trolls' in relation to ICC trials and alleged use of public funds, linking political infighting to accountability issues."
        }
      ]
    },
    {
      "id": "axis_political_trust_corruption_v1",
      "label": "Trust in Political Institutions and Anti-Corruption Efforts",
      "left_pole": "Calls for transparency, investigations into corruption, and holding political figures accountable through legal means.",
      "right_pole": "Skepticism towards investigations, defense of political figures against allegations, and a perception that legal processes are politically motivated or ineffective.",
      "score": 0.0,
      "confidence": 0.05,
      "topics": ["corruption", "political accountability", "COMELEC", "BIR"],
      "created_at": "2026-02-27T04:52:00Z",
      "last_updated": "2026-02-27T06:25:00Z",
      "evidence_log": [
        {
          "post_url": "https://x.com/PhilstarNews/status/2026516865611345983",
          "timestamp": "2026-02-27T04:20:00Z",
          "position": "left",
          "reasoning": "Groups requesting a BIR probe into Sen. Rodante Marcoleta's 'undisclosed campaign contributions'."
        },
        {
          "post_url": "https://x.com/Bert_Control/status/2027123864128610595",
          "timestamp": "2026-02-27T04:20:00Z",
          "position": "left",
          "reasoning": "Call to elevate a case against Marcoleta to the Supreme Court if COMELEC's decision is unfavorable, implying distrust in COMELEC's effectiveness."
        },
        {
          "post_url": "https://x.com/jesusfalcis/status/2026542155037352107",
          "timestamp": "2026-02-27T05:00:00Z",
          "position": "left",
          "reasoning": "Debunking of allegations against Leila De Lima, highlighting the spread of factually incorrect information in political narratives."
        },
        {
          "post_url": "https://x.com/nicoquejano/status/2027212929049972779",
          "timestamp": "2026-02-27T06:15:00Z",
          "position": "left",
          "reasoning": "Allegations of public funds being used to pay 'DDS trolls' to influence ICC trials, undermining trust in political institutions and anti-corruption efforts."
        }
      ]
    },
    {
      "id": "axis_ph_geopolitics_wps_v1",
      "label": "Philippine Geopolitical Alignment in the West Philippine Sea",
      "left_pole": "Strong emphasis on international alliances (US, Japan) and multilateral cooperation to assert sovereignty and security in disputed territories.",
      "right_pole": "Emphasis on independent foreign policy, direct bilateral negotiations, and skepticism towards foreign military presence, potentially prioritizing economic ties over security alliances.",
      "score": 0.0,
      "confidence": 0.05,
      "topics": ["West Philippine Sea", "geopolitics", "alliances", "sovereignty"],
      "created_at": "2026-02-27T04:52:00Z",
      "last_updated": "2026-02-27T06:25:00Z",
      "evidence_log": [
        {
          "post_url": "https://x.com/gmanews/status/2027025225532260415",
          "timestamp": "2026-02-27T04:30:00Z",
          "position": "left",
          "reasoning": "Report on expanded multilateral maritime cooperation involving the Philippines, Japan, and US in the West Philippine Sea, indicating strengthened alliances."
        },
        {
          "post_url": "https://x.com/TeamAFP/status/2027176180630323339",
          "timestamp": "2026-02-27T06:05:00Z",
          "position": "left",
          "reasoning": "Report on continued and expanded Multilateral Maritime Cooperative Activity (MMCA) with Japan and US in the West Philippine Sea, demonstrating reinforced security alliances."
        }
      ]
    },
    {
      "id": "axis_ai_societal_impact_v1",
      "label": "Societal Impact and Ethical Concerns of AI/Robots",
      "left_pole": "Optimism for AI/robotics potential in entertainment, labor augmentation, and scientific advancement, with focus on innovation and benefits.",
      "right_pole": "Concerns about job displacement, ethical implications of autonomous systems (e.g., 'killer robots'), and challenges in distinguishing AI-generated content from reality.",
      "score": 0.0,
      "confidence": 0.05,
      "topics": ["AI", "robots", "job displacement", "ethics", "disinformation"],
      "created_at": "2026-02-27T05:14:00Z",
      "last_updated": "2026-02-27T06:25:00Z",
      "evidence_log": [
        {
          "post_url": "https://x.com/isciverse/status/2027245343747006846",
          "timestamp": "2026-02-27T12:52:00Z",
          "position": "right",
          "reasoning": "AI is taking work from data analysts and research coders, signaling job displacement in specific scientific fields."
        },
        {
          "post_url": "https://x.com/CGTNGlobalBiz/status/2027245166323744892",
          "timestamp": "2026-02-27T12:52:00Z",
          "position": "left",
          "reasoning": "AI-themed park in China showcases robots for entertainment and interactive experiences, highlighting a positive societal integration."
        },
        {
          "post_url": "https://x.com/gotweetworms/status/2027245296359756181",
          "timestamp": "2026-02-27T12:52:00Z",
          "position": "right",
          "reasoning": "Concern expressed over 'armed drones and robots,' raising ethical questions about autonomous weapon systems."
        },
        {
          "post_url": "https://x.com/TWKsicem/status/2027245266458521724",
          "timestamp": "2026-02-27T12:52:00Z",
          "position": "right",
          "reasoning": "Direct reference to 'killer robots,' indicating strong ethical opposition and fear regarding advanced autonomous systems."
        },
        {
          "post_url": "https://x.com/Pixiemetax1/status/2027245229514932474",
          "timestamp": "2026-02-27T12:52:00Z",
          "position": "right",
          "reasoning": "Distinction between robots performing a 'task' and a 'job,' implying limitations and potential for human labor to remain distinct."
        },
        {
          "post_url": "https://x.com/TheFigen_/status/2026709535847756182",
          "timestamp": "2026-02-27T04:10:00Z",
          "position": "right",
          "reasoning": "Public preoccupation with distinguishing AI-generated content from real content, with comments questioning authenticity ('AI or real')."
        },
        {
          "post_url": "https://x.com/gmanews/status/2027107384670171415",
          "timestamp": "2026-02-27T06:05:00Z",
          "position": "right",
          "reasoning": "Report on 'accidental hacking of 7,000 robot vacuums,' highlighting security vulnerabilities of smart devices and privacy concerns."
        }
      ]
    },
    {
      "id": "axis_media_integrity_v1",
      "label": "Integrity of Information and Social Media Manipulation",
      "left_pole": "Advocacy for factual accuracy, critical assessment of sources, and efforts to combat misinformation and deceptive engagement tactics.",
      "right_pole": "Spread of unverified claims, reliance on emotional appeals, and engagement farming strategies to influence public opinion.",
      "score": 0.0,
      "confidence": 0.05,
      "topics": ["disinformation", "fake news", "social media", "engagement"],
      "created_at": "2026-02-27T05:14:00Z",
      "last_updated": "2026-02-27T06:25:00Z",
      "evidence_log": [
        {
          "post_url": "https://x.com/rapplerdotcom/status/2027003723226955942",
          "timestamp": "2026-02-27T04:50:00Z",
          "position": "right",
          "reasoning": "Disinformation turning the internet into a 'battleground for many Filipinos' amidst legal arguments, highlighting the challenge of truth."
        },
        {
          "post_url": "https://x.com/Zexyooo/status/2026915132463575497",
          "timestamp": "2026-02-27T04:50:00Z",
          "position": "right",
          "reasoning": "Aggressive calls for follows ('Only Say Hi We'll Follow You Immediately Let's go') indicating engagement farming tactics."
        },
        {
          "post_url": "https://x.com/Sattv1k/status/2026915132463575497",
          "timestamp": "2026-02-27T04:50:00Z",
          "position": "left",
          "reasoning": "Critique of outdated engagement tactics, advocating for consistent, genuine content, indicating a desire for authentic information."
        },
        {
          "post_url": "https://x.com/nicoquejano/status/2027094501962178982",
          "timestamp": "2026-02-27T04:30:00Z",
          "position": "left",
          "reasoning": "Use of AI (Grok) to 'humiliate DDS' suggests a potential counter-measure against misinformation, though its objectivity needs consideration."
        },
        {
          "post_url": "https://x.com/nicoquejano/status/2027212929049972779",
          "timestamp": "2026-02-27T06:15:00Z",
          "position": "right",
          "reasoning": "Allegations of public funds used to pay 'DDS trolls' for political manipulation, undermining media integrity."
        },
        {
          "post_url": "https://x.com/DaveSi/status/2026971237738831983",
          "timestamp": "2026-02-27T06:05:00Z",
          "position": "right",
          "reasoning": "Accusations of 'trolls' using 'personal homophobic attacks' in response to criticism of Duterte, illustrating aggressive and manipulative online discourse."
        }
      ]
    },
    {
      "id": "axis_geopolitical_rhetoric_v1",
      "label": "Geopolitical Rhetoric vs. Humanitarian Concerns",
      "left_pole": "Prioritizing humanitarian concerns, ethical considerations, and consistency in international relations beyond strategic alliances.",
      "right_pole": "Emphasizing strong national alliances and diplomatic ties, potentially overlooking or remaining silent on human rights issues in allied nations.",
      "score": 0.0,
      "confidence": 0.05,
      "topics": ["geopolitics", "alliances", "humanitarian issues", "international relations"],
      "created_at": "2026-02-27T05:14:00Z",
      "last_updated": "2026-02-27T05:14:00Z",
      "evidence_log": [
        {
          "post_url": "https://x.com/narendramodi/status/2026714966217339017",
          "timestamp": "2026-02-27T04:30:00Z",
          "position": "right",
          "reasoning": "PM Modi highlighting 'Historical connect between India and Israel', emphasizing alliance."
        },
        {
          "post_url": "https://x.com/MR_KG/status/2026714966217339017",
          "timestamp": "2026-02-27T04:30:00Z",
          "position": "left",
          "reasoning": "Critique of India's stance, highlighting silence on 'mosque destructions and iftar in rubble' in the context of India-Israel relations, suggesting a humanitarian concern."
        }
      ]
    },
    {
      "id": "axis_historical_legacy_v1",
      "label": "Interpretation and Legacy of Historical Events",
      "left_pole": "Critical re-evaluation of historical events and figures, emphasizing their contemporary relevance and holding past actions accountable.",
      "right_pole": "Commemoration of historical events that reinforces a specific national narrative, potentially downplaying complex or controversial aspects.",
      "score": 0.0,
      "confidence": 0.05,
      "topics": ["history", "EDSA", "political legacy", "national narrative"],
      "created_at": "2026-02-27T05:14:00Z",
      "last_updated": "2026-02-27T05:14:00Z",
      "evidence_log": [
        {
          "post_url": "https://x.com/PhilstarNews/status/2026582392819855509",
          "timestamp": "2026-02-27T04:30:00Z",
          "position": "right",
          "reasoning": "Sen. Risa Hontiveros commemorating the 40th anniversary of EDSA People Power Revolution, reinforcing its significance."
        },
        {
          "post_url": "https://x.com/ABSCBNNews/status/2026986853996327168",
          "timestamp": "2026-02-27T04:40:00Z",
          "position": "left",
          "reasoning": "Archbishop Socrates Villegas stating 'THIS IS NOT EDSA.', implying a critical view of the current state of affairs compared to the ideals of EDSA."
        }
      ]
    }
  ],
  "axis_creation_rules_version": "1.0"
}